<?xml version="1.0" encoding="UTF-8"?>
<rdf:RDF
   xmlns:bf="http://id.loc.gov/ontologies/bibframe/"
   xmlns:bflc="http://id.loc.gov/ontologies/bflc/"
   xmlns:rdf="http://www.w3.org/1999/02/22-rdf-syntax-ns#"
   xmlns:rdfs="http://www.w3.org/2000/01/rdf-schema#"
>
  <rdf:Description rdf:nodeID="N404439e9d7384a1da2582464312b643d">
    <bf:descriptionLanguage rdf:resource="https://id.loc.gov/vocabulary/languages/eng"/>
    <bflc:catalogerID>ries07</bflc:catalogerID>
    <bf:descriptionConventions rdf:resource="https://id.loc.gov/vocabulary/descriptionConventions/rda"/>
    <bf:creationDate rdf:datatype="http://www.w3.org/2001/XMLSchema#date">2020-02-06</bf:creationDate>
    <bflc:encodingLevel rdf:resource="https://id.loc.gov/vocabulary/menclvl/f"/>
    <rdf:type rdf:resource="http://id.loc.gov/ontologies/bibframe/AdminMetadata"/>
    <bf:generationProcess rdf:nodeID="Nb8f67ee4e3cf4a8fbd3969dde724d6c4"/>
    <bf:source rdf:resource="https://id.loc.gov/vocabulary/organizations/wau"/>
    <bf:status rdf:nodeID="N929e91fe0e4f48bbb589c72ba0fe547a"/>
  </rdf:Description>
  <rdf:Description rdf:about="https://api.sinopia.io/resource/f24bfdbd-32d7-4e79-9199-3e4354df42a7">
    <bf:instanceOf rdf:resource="https://api.sinopia.io/resource/95cb73d5-927f-41c2-9546-9b041de95bf0"/>
    <bf:identifiedBy rdf:resource="https://doi.org/10.1007/978-4-431-56850-6"/>
    <bf:baseMaterial rdf:resource="http://rdaregistry.info/termList/RDAMaterial/1025"/>
    <bf:identifiedBy rdf:nodeID="Na7107ecedf594b00a1d20dede4b38cf1"/>
    <bf:carrier rdf:resource="http://www.rdaregistry.info/termList/RDACarrierType/1008"/>
    <bf:issuance rdf:resource="http://rdaregistry.info/termList/ModeIssue/1001"/>
    <bf:title rdf:nodeID="N4c0e0204ed45468490e7fb87794a5702"/>
    <rdf:type rdf:resource="http://id.loc.gov/ontologies/bibframe/Instance"/>
    <bf:extent rdf:nodeID="Ncec377da99eb43278bd8bdc5935deced"/>
    <bf:identifiedBy rdf:nodeID="Nf0d691c575dc48d3b69d99a77e7b7b7c"/>
    <bf:copyrightDate rdf:datatype="http://www.w3.org/2001/XMLSchema#gYear">©2019</bf:copyrightDate>
    <bf:appliedMaterial rdf:resource="http://rdaregistry.info/termList/RDAMaterial/1017"/>
    <bf:adminMetadata rdf:nodeID="N404439e9d7384a1da2582464312b643d"/>
    <bf:media rdf:resource="http://rdaregistry.info/termList/RDAMediaType/1007"/>
    <bf:dimensions>25 cm</bf:dimensions>
    <bf:provisionActivity rdf:nodeID="N11d4c0b9590a4a339b30c84c992bb8dd"/>
  </rdf:Description>
  <rdf:Description rdf:nodeID="N929e91fe0e4f48bbb589c72ba0fe547a">
    <rdf:type rdf:resource="http://id.loc.gov/ontologies/bibframe/Status"/>
    <bf:code>n</bf:code>
  </rdf:Description>
  <rdf:Description rdf:nodeID="Nb8f67ee4e3cf4a8fbd3969dde724d6c4">
    <rdfs:label rdf:datatype="http://www.w3.org/2001/XMLSchema#dateTime">rml.py SNAPSHOT: 2021-03-19T15:43:32+00:00</rdfs:label>
    <rdf:type rdf:resource="http://id.loc.gov/ontologies/bibframe/GenerationProcess"/>
  </rdf:Description>
  <rdf:Description rdf:nodeID="N11d4c0b9590a4a339b30c84c992bb8dd">
    <bf:agent rdf:nodeID="Nf7849ed4993548b788eec9d52b82a659"/>
    <bf:place rdf:nodeID="N64dcc4ce17e64358a90b4835c9a1b32c"/>
    <rdf:type rdf:resource="http://id.loc.gov/ontologies/bibframe/Publication"/>
  </rdf:Description>
  <rdf:Description rdf:nodeID="Nf0d691c575dc48d3b69d99a77e7b7b7c">
    <rdf:value>ISSN 2364-9119</rdf:value>
    <rdf:type rdf:resource="http://id.loc.gov/ontologies/bibframe/Identifier"/>
  </rdf:Description>
  <rdf:Description rdf:nodeID="Na7107ecedf594b00a1d20dede4b38cf1">
    <rdf:type rdf:resource="http://id.loc.gov/ontologies/bibframe/Identifier"/>
    <rdf:value>ISBN 978-4-431-56848-3</rdf:value>
  </rdf:Description>
  <rdf:Description rdf:nodeID="N4c0e0204ed45468490e7fb87794a5702">
    <bf:mainTitle xml:lang="eng">Tsunami generation and progagation</bf:mainTitle>
    <rdf:type rdf:resource="http://id.loc.gov/ontologies/bibframe/Title"/>
  </rdf:Description>
  <rdf:Description rdf:nodeID="Nf7849ed4993548b788eec9d52b82a659">
    <rdf:type rdf:resource="http://id.loc.gov/ontologies/bibframe/Agent"/>
    <rdfs:label xml:lang="eng">Springer</rdfs:label>
  </rdf:Description>
  <rdf:Description rdf:nodeID="Ncec377da99eb43278bd8bdc5935deced">
    <rdf:type rdf:resource="http://id.loc.gov/ontologies/bibframe/Extent"/>
    <rdfs:label xml:lang="eng">ix, 265 pages</rdfs:label>
  </rdf:Description>
  <rdf:Description rdf:nodeID="N64dcc4ce17e64358a90b4835c9a1b32c">
    <rdfs:label xml:lang="eng">Tokyo</rdfs:label>
    <rdf:type rdf:resource="http://id.loc.gov/ontologies/bibframe/Place"/>
  </rdf:Description>
</rdf:RDF>
