<?xml version="1.0" encoding="UTF-8"?>
<rdf:RDF
   xmlns:bf="http://id.loc.gov/ontologies/bibframe/"
   xmlns:bflc="http://id.loc.gov/ontologies/bflc/"
   xmlns:madsrdf="http://www.loc.gov/mads/rdf/v1#"
   xmlns:owl="http://www.w3.org/2002/07/owl#"
   xmlns:rdf="http://www.w3.org/1999/02/22-rdf-syntax-ns#"
   xmlns:rdfs="http://www.w3.org/2000/01/rdf-schema#"
   xmlns:skos="http://www.w3.org/2004/02/skos/core#"
>
  <rdf:Description rdf:nodeID="Ne09590406973491495b13cc5500fdfd5">
    <bf:role rdf:resource="http://id.loc.gov/vocabulary/relators/aut"/>
    <rdf:type rdf:resource="http://id.loc.gov/ontologies/bibframe/Contribution"/>
    <bf:agent rdf:resource="http://id.loc.gov/authorities/names/n86072799"/>
  </rdf:Description>
  <rdf:Description rdf:about="https://api.sinopia.io/resource/be0e7f01-6c27-4725-9704-4318193ac7da">
    <bf:subject rdf:nodeID="Nf2ca36cdfae74994bedf2fb54cc2e47f"/>
    <bf:subject rdf:nodeID="Nc9b9e37407f8478e8a8cfe7ec9223e39"/>
    <bf:contribution rdf:nodeID="Ne09590406973491495b13cc5500fdfd5"/>
    <bf:subject rdf:nodeID="N9c057142ce4b4053a54fbcdf4fe14455"/>
    <bf:genreForm rdf:nodeID="N5a3ba8fe9a3442d58162f59a6608eb70"/>
    <bf:genreForm rdf:nodeID="N0c4f4795e4c84992aa7acf6f9aa41ef6"/>
    <bf:adminMetadata rdf:nodeID="N6d51aa1c229d4373a8926a57bb658130"/>
    <skos:prefLabel xml:lang="eng">Strickler, Dee. Wayside wildflowers of the Pacific Northwest</skos:prefLabel>
    <rdf:type rdf:resource="http://id.loc.gov/ontologies/bibframe/Work"/>
    <bf:subject rdf:nodeID="N04aa43f24b9241c0acaa927e4aefe4a4"/>
    <bf:originDate>1993</bf:originDate>
    <bf:title rdf:nodeID="N584518c43ede417f9d42b61cc5546c12"/>
    <owl:sameAs rdf:resource="https://api.sinopia.io/resource/1204a5b5-49c0-40b0-b7ce-cdee99e8e54b"/>
    <skos:altLabel xml:lang="eng">Strickler, Zoe. Wayside wildflowers of the Pacific Northwest</skos:altLabel>
  </rdf:Description>
  <rdf:Description rdf:nodeID="N04aa43f24b9241c0acaa927e4aefe4a4">
    <rdfs:label>Roadside plants -- Northwest, Pacific -- Identification</rdfs:label>
    <rdf:type rdf:resource="http://www.loc.gov/mads/rdf/v1#Authority"/>
    <madsrdf:authoritativeLabel>Roadside plants -- Northwest, Pacific -- Identification</madsrdf:authoritativeLabel>
  </rdf:Description>
  <rdf:Description rdf:nodeID="Ne91c654229a542d8a0e91a2774352cb3">
    <rdf:type rdf:resource="http://id.loc.gov/ontologies/bibframe/Status"/>
    <bf:code>n</bf:code>
  </rdf:Description>
  <rdf:Description rdf:nodeID="N584518c43ede417f9d42b61cc5546c12">
    <rdf:type rdf:resource="http://id.loc.gov/ontologies/bibframe/Title"/>
    <bf:mainTitle xml:lang="eng">Wayside wildflowers of the Pacific Northwest</bf:mainTitle>
  </rdf:Description>
  <rdf:Description rdf:nodeID="N6d51aa1c229d4373a8926a57bb658130">
    <bflc:catalogerID>pfreeman</bflc:catalogerID>
    <bflc:encodingLevel rdf:resource="https://id.loc.gov/vocabulary/menclvl/f"/>
    <rdf:type rdf:resource="http://id.loc.gov/ontologies/bibframe/AdminMetadata"/>
    <bf:generationProcess rdf:nodeID="N18d7d0be8e0140b880dec973d6bae01e"/>
    <bf:creationDate rdf:datatype="http://www.w3.org/2001/XMLSchema#date">2021-05-10</bf:creationDate>
    <bf:descriptionConventions rdf:resource="https://id.loc.gov/vocabulary/descriptionConventions/rda"/>
    <bf:source rdf:resource="https://id.loc.gov/vocabulary/organizations/wau"/>
    <bf:descriptionAuthentication rdf:resource="http://id.loc.gov/vocabulary/marcauthen/pcc"/>
    <bf:descriptionLanguage rdf:resource="https://id.loc.gov/vocabulary/languages/eng"/>
    <bf:status rdf:nodeID="Ne91c654229a542d8a0e91a2774352cb3"/>
  </rdf:Description>
  <rdf:Description rdf:nodeID="N9c057142ce4b4053a54fbcdf4fe14455">
    <rdf:type rdf:resource="http://www.loc.gov/mads/rdf/v1#Authority"/>
    <rdfs:label>Wildflowers -- Northwest, Pacific -- Pictorial works</rdfs:label>
    <madsrdf:authoritativeLabel>Wildflowers -- Northwest, Pacific -- Pictorial works</madsrdf:authoritativeLabel>
  </rdf:Description>
  <rdf:Description rdf:nodeID="Nc9b9e37407f8478e8a8cfe7ec9223e39">
    <madsrdf:authoritativeLabel>Wild flowers -- Northwest, Pacific -- Identification</madsrdf:authoritativeLabel>
    <rdf:type rdf:resource="http://www.loc.gov/mads/rdf/v1#Authority"/>
    <rdfs:label>Wild flowers -- Northwest, Pacific -- Identification</rdfs:label>
  </rdf:Description>
  <rdf:Description rdf:nodeID="N0c4f4795e4c84992aa7acf6f9aa41ef6">
    <rdfs:label>Illustrated works</rdfs:label>
    <rdf:type rdf:resource="http://id.loc.gov/ontologies/bibframe/GenreForm"/>
  </rdf:Description>
  <rdf:Description rdf:nodeID="N18d7d0be8e0140b880dec973d6bae01e">
    <rdfs:label>rml.py SNAPSHOT: 2021-05-10T13:08:04+00:00</rdfs:label>
    <rdf:type rdf:resource="http://id.loc.gov/ontologies/bibframe/GenerationProcess"/>
  </rdf:Description>
  <rdf:Description rdf:nodeID="Nf2ca36cdfae74994bedf2fb54cc2e47f">
    <madsrdf:authoritativeLabel>Roadside plants -- Northwest, Pacific -- Pictorial works.</madsrdf:authoritativeLabel>
    <rdfs:label>Roadside plants -- Northwest, Pacific -- Pictorial works.</rdfs:label>
    <rdf:type rdf:resource="http://www.loc.gov/mads/rdf/v1#Authority"/>
  </rdf:Description>
  <rdf:Description rdf:nodeID="N5a3ba8fe9a3442d58162f59a6608eb70">
    <rdf:type rdf:resource="http://id.loc.gov/ontologies/bibframe/GenreForm"/>
    <rdfs:label>Field guides</rdfs:label>
  </rdf:Description>
</rdf:RDF>
