<?xml version="1.0" encoding="UTF-8"?>
<rdf:RDF
   xmlns:bf="http://id.loc.gov/ontologies/bibframe/"
   xmlns:bflc="http://id.loc.gov/ontologies/bflc/"
   xmlns:rdf="http://www.w3.org/1999/02/22-rdf-syntax-ns#"
   xmlns:rdfs="http://www.w3.org/2000/01/rdf-schema#"
>
  <rdf:Description rdf:nodeID="Nd22fbbb8a1424f328936c61af25eff0d">
    <bf:status rdf:nodeID="N70e65dc2c65a4cde9b12f6bdba8ef945"/>
    <bf:source rdf:resource="https://id.loc.gov/vocabulary/organizations/wau"/>
    <bf:creationDate rdf:datatype="http://www.w3.org/2001/XMLSchema#date">2020-04-30</bf:creationDate>
    <bflc:encodingLevel rdf:resource="https://id.loc.gov/vocabulary/menclvl/f"/>
    <bf:generationProcess rdf:nodeID="N820b9968c4074984a2e97e639d24e20e"/>
    <bflc:catalogerID xml:lang="eng">pfreeman</bflc:catalogerID>
    <bf:descriptionLanguage rdf:resource="https://id.loc.gov/vocabulary/languages/eng"/>
    <rdf:type rdf:resource="http://id.loc.gov/ontologies/bibframe/AdminMetadata"/>
    <bf:descriptionConventions rdf:resource="https://id.loc.gov/vocabulary/descriptionConventions/rda"/>
  </rdf:Description>
  <rdf:Description rdf:about="https://api.sinopia.io/resource/a143aa19-f5ec-4084-b33f-40ac515ac2cf">
    <rdf:type rdf:resource="http://id.loc.gov/ontologies/bibframe/Item"/>
    <bf:sublocation rdf:nodeID="Nda435441610a411abfa4e4c63d184885"/>
    <bf:adminMetadata rdf:nodeID="Nd22fbbb8a1424f328936c61af25eff0d"/>
    <bf:itemOf rdf:resource="https://api.sinopia.io/resource/a36e9ced-6550-4bcc-b37d-aa7e8a0e123e"/>
    <bf:physicalLocation xml:lang="eng">Pacific Northwest books</bf:physicalLocation>
    <bf:classification rdf:nodeID="N15d39e1dd6b4429f85842d75699bcf21"/>
    <bf:heldBy rdf:resource="https://id.loc.gov/vocabulary/organizations/wau"/>
  </rdf:Description>
  <rdf:Description rdf:nodeID="N820b9968c4074984a2e97e639d24e20e">
    <rdf:type rdf:resource="http://id.loc.gov/ontologies/bibframe/GenerationProcess"/>
    <rdfs:label rdf:datatype="http://www.w3.org/2001/XMLSchema#dateTime">rml.py SNAPSHOT: 2021-03-19T15:48:53+00:00</rdfs:label>
  </rdf:Description>
  <rdf:Description rdf:nodeID="N15d39e1dd6b4429f85842d75699bcf21">
    <bf:classificationPortion>QK192</bf:classificationPortion>
    <rdf:type rdf:resource="http://id.loc.gov/ontologies/bibframe/ClassificationLcc"/>
    <bf:itemPortion>.M36 1979</bf:itemPortion>
  </rdf:Description>
  <rdf:Description rdf:nodeID="N70e65dc2c65a4cde9b12f6bdba8ef945">
    <bf:code>n</bf:code>
    <rdf:type rdf:resource="http://id.loc.gov/ontologies/bibframe/Status"/>
  </rdf:Description>
  <rdf:Description rdf:nodeID="Nda435441610a411abfa4e4c63d184885">
    <rdf:type rdf:resource="http://id.loc.gov/ontologies/bibframe/Sublocation"/>
    <rdfs:label xml:lang="eng">bookshelf</rdfs:label>
  </rdf:Description>
</rdf:RDF>
