{
  "@graph": [{
    "@id": "_:b0",
    "@type": "http://id.loc.gov/ontologies/bibframe/AdminMetadata",
    "catalogerID": {
      "@language": "zxx",
      "@value": "dbrookin"
    },
    "encodingLevel": "https://id.loc.gov/vocabulary/menclvl/f",
    "creationDate": {
      "@language": "zxx",
      "@value": "2020-03-24"
    },
    "descriptionConventions": "https://id.loc.gov/vocabulary/descriptionConventions/rda",
    "descriptionLanguage": "https://id.loc.gov/vocabulary/languages/eng",
    "source": "https://id.loc.gov/vocabulary/organizations/wau",
    "status": "_:b3"
  }, {
    "@id": "_:b1",
    "@type": ["as:Update", "prov:Activity"],
    "atTime": "2020-03-24T17:12:01.534Z",
    "wasAssociatedWith": "https://cognito-idp.us-west-2.amazonaws.com/us-west-2_JLxtCILIV/85df7037-d85a-4ce2-9214-6bfea0f58e79"
  }, {
    "@id": "_:b2",
    "@type": ["as:Create", "prov:Activity"],
    "atTime": "2020-03-24T17:06:07.416Z",
    "wasAssociatedWith": "https://cognito-idp.us-west-2.amazonaws.com/us-west-2_JLxtCILIV/85df7037-d85a-4ce2-9214-6bfea0f58e79"
  }, {
    "@id": "_:b3",
    "@type": "http://id.loc.gov/ontologies/bibframe/Status",
    "code": {
      "@language": "zxx",
      "@value": "n"
    }
  }, {
    "@id": "http://rdaregistry.info/termList/ModeIssue/1005",
    "label": "multiple unit"
  }, {
    "@id": "http://rdaregistry.info/termList/RDAMediaType/1007",
    "label": "unmediated"
  }, {
    "@id": "http://www.rdaregistry.info/termList/RDACarrierType/1008",
    "label": "volume"
  }, {
    "@id": "https://id.loc.gov/vocabulary/descriptionConventions/rda",
    "label": "Resource Description and Access"
  }, {
    "@id": "https://id.loc.gov/vocabulary/languages/eng",
    "label": "English"
  }, {
    "@id": "https://id.loc.gov/vocabulary/menclvl/f",
    "label": "full"
  }, {
    "@id": "https://id.loc.gov/vocabulary/organizations/wau",
    "label": ["WAU", "WaU"]
  }, {
    "@id": "https://trellis.sinopia.io/repository/washington/2616e60e-7a10-4141-b516-174173a1bde4",
    "@type": "http://rdaregistry.info/Elements/c/C10007",
    "adminMetadata": "_:b0",
    "P30001": "http://www.rdaregistry.info/termList/RDACarrierType/1008",
    "P30002": "http://rdaregistry.info/termList/RDAMediaType/1007",
    "P30003": "http://rdaregistry.info/termList/ModeIssue/1005",
    "P30011": {
      "@language": "zxx",
      "@value": "[1917?]-"
    },
    "P30086": {
      "@language": "rus",
      "@value": "Шанхай, Китай"
    },
    "P30088": {
      "@language": "rus",
      "@value": "Иркутскъ"
    },
    "P30105": [{
      "@language": "rus",
      "@value": "М.Г. Айзенштадтъ и М.И. Дайхесъ"
    }, {
      "@language": "rus",
      "@value": "съ участіемъ художника академика М.Л. Маймона"
    }],
    "P30128": [{
      "@language": "rus",
      "@value": "Nashim deti︠a︡m"
    }, {
      "@language": "rus",
      "@value": "Nashimʺ di︠e︡ti︠a︡m"
    }, {
      "@language": "rus",
      "@value": "Нашим детям"
    }],
    "P30133": {
      "@language": "rus",
      "@value": "Изданіе третье"
    },
    "P30139": "https://trellis.sinopia.io/repository/washington/bd941aa0-25fe-42f2-b8e5-fca14aece262",
    "P30142": {
      "@language": "rus",
      "@value": "хрестоматія на русскомъ языкѣ для еврейскихъ дѣтей въ школѣ и семьѣ"
    },
    "P30156": {
      "@language": "rus",
      "@value": "Нашимъ дѣтям"
    },
    "P30174": {
      "@language": "rus",
      "@value": "Типо-Литографія Commercial Press"
    },
    "P30176": {
      "@language": "rus",
      "@value": "Изданіе Национальнаго Совѣта Евреевъ Сибири и Урала"
    },
    "P30182": {
      "@language": "eng",
      "@value": "volumes"
    },
    "hasResourceTemplate": "WAU:RT:RDA:Manifestation:serial",
    "wasGeneratedBy": ["_:b1", "_:b2"],
    "heldBy": "https://id.loc.gov/vocabulary/organizations/wau"
  }, {
    "@id": "https://trellis.sinopia.io/repository/washington/bd941aa0-25fe-42f2-b8e5-fca14aece262",
    "label": "https://trellis.sinopia.io/repository/washington/bd941aa0-25fe-42f2-b8e5-fca14aece262"
  }],
  "@context": {
    "label": {
      "@id": "http://www.w3.org/2000/01/rdf-schema#label"
    },
    "P30128": {
      "@id": "http://rdaregistry.info/Elements/m/P30128"
    },
    "P30139": {
      "@id": "http://rdaregistry.info/Elements/m/P30139",
      "@type": "@id"
    },
    "P30088": {
      "@id": "http://rdaregistry.info/Elements/m/P30088"
    },
    "P30156": {
      "@id": "http://rdaregistry.info/Elements/m/P30156"
    },
    "heldBy": {
      "@id": "https://doi.org/10.6069/uwlib.55.d.4#heldBy",
      "@type": "@id"
    },
    "hasResourceTemplate": {
      "@id": "http://sinopia.io/vocabulary/hasResourceTemplate"
    },
    "P30182": {
      "@id": "http://rdaregistry.info/Elements/m/P30182"
    },
    "P30002": {
      "@id": "http://rdaregistry.info/Elements/m/P30002",
      "@type": "@id"
    },
    "P30003": {
      "@id": "http://rdaregistry.info/Elements/m/P30003",
      "@type": "@id"
    },
    "P30086": {
      "@id": "http://rdaregistry.info/Elements/m/P30086"
    },
    "adminMetadata": {
      "@id": "http://id.loc.gov/ontologies/bibframe/adminMetadata",
      "@type": "@id"
    },
    "P30142": {
      "@id": "http://rdaregistry.info/Elements/m/P30142"
    },
    "P30176": {
      "@id": "http://rdaregistry.info/Elements/m/P30176"
    },
    "wasGeneratedBy": {
      "@id": "http://www.w3.org/ns/prov#wasGeneratedBy",
      "@type": "@id"
    },
    "P30001": {
      "@id": "http://rdaregistry.info/Elements/m/P30001",
      "@type": "@id"
    },
    "P30133": {
      "@id": "http://rdaregistry.info/Elements/m/P30133"
    },
    "P30011": {
      "@id": "http://rdaregistry.info/Elements/m/P30011"
    },
    "P30105": {
      "@id": "http://rdaregistry.info/Elements/m/P30105"
    },
    "P30174": {
      "@id": "http://rdaregistry.info/Elements/m/P30174"
    },
    "atTime": {
      "@id": "http://www.w3.org/ns/prov#atTime",
      "@type": "http://www.w3.org/2001/XMLSchema#dateTime"
    },
    "wasAssociatedWith": {
      "@id": "http://www.w3.org/ns/prov#wasAssociatedWith",
      "@type": "@id"
    },
    "code": {
      "@id": "http://id.loc.gov/ontologies/bibframe/code"
    },
    "catalogerID": {
      "@id": "http://id.loc.gov/ontologies/bflc/catalogerID"
    },
    "status": {
      "@id": "http://id.loc.gov/ontologies/bibframe/status",
      "@type": "@id"
    },
    "encodingLevel": {
      "@id": "http://id.loc.gov/ontologies/bflc/encodingLevel",
      "@type": "@id"
    },
    "descriptionConventions": {
      "@id": "http://id.loc.gov/ontologies/bibframe/descriptionConventions",
      "@type": "@id"
    },
    "source": {
      "@id": "http://id.loc.gov/ontologies/bibframe/source",
      "@type": "@id"
    },
    "descriptionLanguage": {
      "@id": "http://id.loc.gov/ontologies/bibframe/descriptionLanguage",
      "@type": "@id"
    },
    "creationDate": {
      "@id": "http://id.loc.gov/ontologies/bibframe/creationDate"
    },
    "schema": "http://schema.org/",
    "owl": "http://www.w3.org/2002/07/owl#",
    "xsd": "http://www.w3.org/2001/XMLSchema#",
    "skos": "http://www.w3.org/2004/02/skos/core#",
    "memento": "http://mementoweb.org/ns#",
    "rdfs": "http://www.w3.org/2000/01/rdf-schema#",
    "acl": "http://www.w3.org/ns/auth/acl#",
    "geo": "http://www.w3.org/2003/01/geo/wgs84_pos#",
    "dc11": "http://purl.org/dc/elements/1.1/",
    "as": "https://www.w3.org/ns/activitystreams#",
    "rdf": "http://www.w3.org/1999/02/22-rdf-syntax-ns#",
    "ldp": "http://www.w3.org/ns/ldp#",
    "time": "http://www.w3.org/2006/time#",
    "prov": "http://www.w3.org/ns/prov#",
    "dc": "http://purl.org/dc/terms/"
  }
}
