{"data": [{"@id": "https://api.sinopia.io/resource/1f45540c-4453-49c1-bc60-13c41e58a6b3", "@type": ["http://id.loc.gov/ontologies/bibframe/Work"], "http://id.loc.gov/ontologies/bibframe/adminMetadata": [{"@id": "_:N8fdb5857c23b4896becea8cc88c6ce34"}], "http://id.loc.gov/ontologies/bibframe/contribution": [{"@id": "_:N63bc1a9be20b4b97b76d656e65cef576"}], "http://id.loc.gov/ontologies/bibframe/subject": [{"@id": "_:Na516e051afc24453ac5f868753676478"}], "http://id.loc.gov/ontologies/bibframe/title": [{"@id": "_:Nfffa9b8bbaa04e768ee3d635b1c85c47"}, {"@id": "_:N8b51f86ba65f495d8a9ef7df60fef756"}, {"@id": "_:N53d9fd18ae5e4ecb876b70fbfa25543e"}], "http://sinopia.io/vocabulary/hasResourceTemplate": [{"@value": "WAU:RT:BF2:Works"}], "http://www.w3.org/2002/07/owl#sameAs": [{"@id": "https://api.sinopia.io/resource/a3186ad1-a262-4206-a35d-9598b7f11d27"}], "http://www.w3.org/2004/02/skos/core#altLabel": [{"@language": "ukr", "@value": "\u041a\u043e\u043f\u0430\u0447, \u041e\u043b\u0435\u043a\u0441\u0430\u043d\u0434\u0440\u0430.\u041c\u043e\u0432\u043e\u0441\u0442\u0438\u043b\u044c \u041e\u043b\u044c\u0433\u0438 \u041a\u043e\u0431\u0438\u043b\u044f\u043d\u0441\u044c\u043a\u043e\u0457"}], "http://www.w3.org/2004/02/skos/core#prefLabel": [{"@language": "ukr", "@value": "Kopach, Oleksandra. Movostyl\u02b9 Ol\u02b9hy Kobyli\ufe20a\ufe21ns\u02b9koi\u0308"}]}, {"@id": "_:Na516e051afc24453ac5f868753676478", "@type": ["http://www.loc.gov/mads/rdf/v1#Authority"], "http://www.loc.gov/mads/rdf/v1#authoritativeLabel": [{"@value": "Kobyli\ufe20a\ufe21ns\u02b9ka, Ol\u02b9ha, 1863-1942--Language."}], "http://www.w3.org/2000/01/rdf-schema#label": [{"@value": "Kobyli\ufe20a\ufe21ns\u02b9ka, Ol\u02b9ha, 1863-1942--Language."}]}, {"@id": "_:N8fdb5857c23b4896becea8cc88c6ce34", "@type": ["http://id.loc.gov/ontologies/bibframe/AdminMetadata"], "http://id.loc.gov/ontologies/bflc/catalogerId": [{"@value": "dbrookin"}], "http://id.loc.gov/ontologies/bflc/encodingLevel": [{"@id": "https://id.loc.gov/vocabulary/menclvl/f"}], "http://id.loc.gov/ontologies/bibframe/changeDate": [{"@type": "http://www.w3.org/2001/XMLSchema#date", "@value": "2021-07-08"}], "http://id.loc.gov/ontologies/bibframe/creationDate": [{"@type": "http://www.w3.org/2001/XMLSchema#date", "@value": "2021-05-11"}], "http://id.loc.gov/ontologies/bibframe/descriptionConventions": [{"@id": "https://id.loc.gov/vocabulary/descriptionConventions/rda"}], "http://id.loc.gov/ontologies/bibframe/descriptionLanguage": [{"@id": "https://id.loc.gov/vocabulary/languages/eng"}], "http://id.loc.gov/ontologies/bibframe/generationProcess": [{"@id": "_:Nf5cda29944e6407fbc1990cfb04dcb39"}], "http://id.loc.gov/ontologies/bibframe/source": [{"@id": "https://id.loc.gov/vocabulary/organizations/wau"}], "http://id.loc.gov/ontologies/bibframe/status": [{"@id": "_:N602549cf22d34e50964d85cf5936733e"}]}, {"@id": "_:Nf5cda29944e6407fbc1990cfb04dcb39", "@type": ["http://id.loc.gov/ontologies/bibframe/GenerationProcess"], "http://www.w3.org/2000/01/rdf-schema#label": [{"@value": "rda-to-bf-for-sinopia.py SNAPSHOT: 2021-07-08T14:47:39"}]}, {"@id": "_:N602549cf22d34e50964d85cf5936733e", "@type": ["http://id.loc.gov/ontologies/bibframe/Status"], "http://id.loc.gov/ontologies/bibframe/code": [{"@value": "n"}]}, {"@id": "_:Nfffa9b8bbaa04e768ee3d635b1c85c47", "@type": ["http://id.loc.gov/ontologies/bibframe/VariantTitle"], "http://id.loc.gov/ontologies/bibframe/mainTitle": [{"@language": "eng", "@value": "Language and style of Ol'ha Kobylianska"}]}, {"@id": "_:N8b51f86ba65f495d8a9ef7df60fef756", "@type": ["http://id.loc.gov/ontologies/bibframe/Title"], "http://id.loc.gov/ontologies/bibframe/mainTitle": [{"@language": "ukr", "@value": "Movostyl\u02b9 Ol\u02b9hy Kobyli\ufe20a\ufe21ns\u02b9koi\u0308"}]}, {"@id": "_:N53d9fd18ae5e4ecb876b70fbfa25543e", "@type": ["http://id.loc.gov/ontologies/bibframe/VariantTitle"], "http://id.loc.gov/ontologies/bibframe/mainTitle": [{"@language": "ukr", "@value": "\u041c\u043e\u0432\u043e\u0441\u0442\u0438\u043b\u044c \u041e\u043b\u044c\u0433\u0438 \u041a\u043e\u0431\u0438\u043b\u044f\u043d\u0441\u044c\u043a\u043e\u0457"}]}, {"@id": "_:N63bc1a9be20b4b97b76d656e65cef576", "@type": ["http://id.loc.gov/ontologies/bibframe/Contribution"], "http://id.loc.gov/ontologies/bibframe/agent": [{"@id": "_:Nc4b29b8cbd5c4d67b8fd43902db413e0"}], "http://id.loc.gov/ontologies/bibframe/role": [{"@id": "http://id.loc.gov/vocabulary/relators/aut"}]}, {"@id": "_:Nc4b29b8cbd5c4d67b8fd43902db413e0", "@type": ["http://id.loc.gov/ontologies/bibframe/Agent"], "http://www.w3.org/2000/01/rdf-schema#label": [{"@value": "Kopach, Oleksandra"}]}], "user": "mcm104", "group": "washington", "templateId": "WAU:RT:BF2:Works", "types": ["http://id.loc.gov/ontologies/bibframe/Work"], "id": "1f45540c-4453-49c1-bc60-13c41e58a6b3", "uri": "https://api.sinopia.io/resource/1f45540c-4453-49c1-bc60-13c41e58a6b3", "timestamp": "2021-07-08T15:02:04"}