<?xml version="1.0" encoding="UTF-8"?>
<rdf:RDF
   xmlns:bf="http://id.loc.gov/ontologies/bibframe/"
   xmlns:bflc="http://id.loc.gov/ontologies/bflc/"
   xmlns:owl="http://www.w3.org/2002/07/owl#"
   xmlns:rdf="http://www.w3.org/1999/02/22-rdf-syntax-ns#"
   xmlns:rdfs="http://www.w3.org/2000/01/rdf-schema#"
   xmlns:skos="http://www.w3.org/2004/02/skos/core#"
>
  <rdf:Description rdf:about="https://api.stage.sinopia.io/resource/061fa6a1-c335-4c91-b0e8-925d2911dda4">
    <bf:title rdf:nodeID="N150e6465b8fd4de8898f69e32306e869"/>
    <bf:notation rdf:nodeID="Ndc3ba812d5014fa0b127e668134f23fb"/>
    <bf:originDate rdf:datatype="http://www.w3.org/2001/XMLSchema#gYear">1953-01-01</bf:originDate>
    <owl:sameAs rdf:resource="https://api.sinopia.io/resource/ddee57d3-5e03-43f3-ac3f-673231e23928"/>
    <skos:prefLabel xml:lang="eng">Christie, Agatha, 1890-1976. Pocket full of rye. English</skos:prefLabel>
    <bf:summary rdf:nodeID="Nedc31215e7224dd9976337792869936e"/>
    <bf:expressionOf rdf:resource="https://api.sinopia.io/resource/ac38e3ac-3ff6-4c88-a1e9-f55a6fc5e12a"/>
    <bf:content rdf:resource="http://rdaregistry.info/termList/RDAContentType/1020"/>
    <bf:language rdf:resource="http://id.loc.gov/vocabulary/languages/eng"/>
    <bf:adminMetadata rdf:nodeID="N2812eb5c2ba04d1e8b0b500225358565"/>
    <rdf:type rdf:resource="http://id.loc.gov/ontologies/bibframe/Work"/>
  </rdf:Description>
  <rdf:Description rdf:nodeID="N2812eb5c2ba04d1e8b0b500225358565">
    <bflc:catalogerID>cec23</bflc:catalogerID>
    <bf:status rdf:nodeID="N1be435da0e62447a9776b716676c88e0"/>
    <bflc:encodingLevel rdf:resource="https://id.loc.gov/vocabulary/menclvl/f"/>
    <bf:descriptionLanguage rdf:resource="https://id.loc.gov/vocabulary/languages/eng"/>
    <rdf:type rdf:resource="http://id.loc.gov/ontologies/bibframe/AdminMetadata"/>
    <bf:source rdf:resource="https://id.loc.gov/vocabulary/organizations/wau"/>
    <bf:generationProcess rdf:nodeID="Nfd006ff2af5a425aad38a4568c99cbae"/>
    <bf:creationDate rdf:datatype="http://www.w3.org/2001/XMLSchema#date">2020-01-28</bf:creationDate>
    <bf:descriptionConventions rdf:resource="https://id.loc.gov/vocabulary/descriptionConventions/rda"/>
  </rdf:Description>
  <rdf:Description rdf:nodeID="N1be435da0e62447a9776b716676c88e0">
    <rdf:type rdf:resource="http://id.loc.gov/ontologies/bibframe/Status"/>
    <bf:code>n</bf:code>
  </rdf:Description>
  <rdf:Description rdf:nodeID="Ndc3ba812d5014fa0b127e668134f23fb">
    <rdf:type rdf:resource="http://id.loc.gov/ontologies/bibframe/Script"/>
    <rdfs:label xml:lang="eng">Latin</rdfs:label>
  </rdf:Description>
  <rdf:Description rdf:nodeID="N150e6465b8fd4de8898f69e32306e869">
    <rdf:type rdf:resource="http://id.loc.gov/ontologies/bibframe/Title"/>
    <bf:mainTitle xml:lang="eng">Pocket full of rye</bf:mainTitle>
  </rdf:Description>
  <rdf:Description rdf:nodeID="Nfd006ff2af5a425aad38a4568c99cbae">
    <rdf:type rdf:resource="http://id.loc.gov/ontologies/bibframe/GenerationProcess"/>
    <rdfs:label rdf:datatype="http://www.w3.org/2001/XMLSchema#dateTime">rml.py SNAPSHOT: 2021-04-13T17:14:59+00:00</rdfs:label>
  </rdf:Description>
  <rdf:Description rdf:nodeID="Nedc31215e7224dd9976337792869936e">
    <rdf:type rdf:resource="http://id.loc.gov/ontologies/bibframe/Summary"/>
    <rdfs:label xml:lang="eng">"It started with a spot of tea. It ended in tragedy when the wealthy Rex Fortescue sipped his last cup, fell ill, and died. The only clue: a pocketful of rye found on the victim. The murder seemed without rhyme or reason--until the shrewd Miss Marple recalled that delightful nursery rhyme 'Sing a Song of Sixpence.' A playful hint, indeed. But the spinster sleuth knew that murder was anything but child's play..."--Page 4 of cover.</rdfs:label>
  </rdf:Description>
</rdf:RDF>
