<?xml version="1.0" encoding="UTF-8"?>
<rdf:RDF
   xmlns:bf="http://id.loc.gov/ontologies/bibframe/"
   xmlns:bflc="http://id.loc.gov/ontologies/bflc/"
   xmlns:owl="http://www.w3.org/2002/07/owl#"
   xmlns:rdf="http://www.w3.org/1999/02/22-rdf-syntax-ns#"
   xmlns:rdfs="http://www.w3.org/2000/01/rdf-schema#"
>
  <rdf:Description rdf:about="https://api.stage.sinopia.io/resource/8dc35d3f-2598-4e86-b6f4-5134535905de">
    <bf:contribution rdf:nodeID="Nc3008a529f364366b0b4d41a6feadb21"/>
    <bf:summary rdf:nodeID="Nf37ae9a5a37240d98447b26cdecd084a"/>
    <bf:notation rdf:nodeID="Nea630ffc11ae4601ba8722be2fa76701"/>
    <bf:adminMetadata rdf:nodeID="N10c40064a9964f6d8f58c70363a16f4c"/>
    <bf:language rdf:resource="http://id.loc.gov/vocabulary/languages/eng"/>
    <bf:colorContent rdf:resource="http://rdaregistry.info/termList/RDAColourContent/1003"/>
    <bf:expressionOf rdf:resource="https://api.sinopia.io/resource/b4e1fc6d-8c29-447a-94a8-fed3132ca629"/>
    <rdf:type rdf:resource="http://id.loc.gov/ontologies/bibframe/Work"/>
    <bf:content rdf:resource="http://rdaregistry.info/termList/RDAContentType/1020"/>
    <bf:originDate>1993</bf:originDate>
    <bf:supplementaryContent rdf:nodeID="Nc5390653a56549d48c7c816ac03c82d9"/>
    <owl:sameAs rdf:resource="https://api.sinopia.io/resource/9925a8e6-ed73-4817-acbb-e844b70df187"/>
  </rdf:Description>
  <rdf:Description rdf:nodeID="N10c40064a9964f6d8f58c70363a16f4c">
    <bf:generationProcess rdf:nodeID="Nbf54256e37ba488e862a017314b3eddd"/>
    <bflc:catalogerID>pfreeman</bflc:catalogerID>
    <bf:descriptionLanguage rdf:resource="https://id.loc.gov/vocabulary/languages/eng"/>
    <bf:descriptionConventions rdf:resource="https://id.loc.gov/vocabulary/descriptionConventions/rda"/>
    <bf:creationDate rdf:datatype="http://www.w3.org/2001/XMLSchema#date">2021-05-04</bf:creationDate>
    <bf:status rdf:nodeID="N20eedfc6389e4ad19323338f3947977f"/>
    <bf:descriptionAuthentication rdf:resource="http://id.loc.gov/vocabulary/marcauthen/pcc"/>
    <rdf:type rdf:resource="http://id.loc.gov/ontologies/bibframe/AdminMetadata"/>
    <bflc:encodingLevel rdf:resource="https://id.loc.gov/vocabulary/menclvl/f"/>
    <bf:source rdf:resource="https://id.loc.gov/vocabulary/organizations/wau"/>
  </rdf:Description>
  <rdf:Description rdf:nodeID="N20eedfc6389e4ad19323338f3947977f">
    <bf:code>n</bf:code>
    <rdf:type rdf:resource="http://id.loc.gov/ontologies/bibframe/Status"/>
  </rdf:Description>
  <rdf:Description rdf:nodeID="Nf37ae9a5a37240d98447b26cdecd084a">
    <rdfs:label xml:lang="eng">Features wildflowers along the roads and highways of the Pacific Northwest.</rdfs:label>
    <rdf:type rdf:resource="http://id.loc.gov/ontologies/bibframe/Summary"/>
  </rdf:Description>
  <rdf:Description rdf:nodeID="Nbf54256e37ba488e862a017314b3eddd">
    <rdfs:label>rml.py SNAPSHOT: 2021-05-04T13:32:09+00:00</rdfs:label>
    <rdf:type rdf:resource="http://id.loc.gov/ontologies/bibframe/GenerationProcess"/>
  </rdf:Description>
  <rdf:Description rdf:nodeID="Na8d4e2889262436f8674dd1ca36c2872">
    <rdfs:label>Strickler, Zoe</rdfs:label>
    <rdf:type rdf:resource="http://id.loc.gov/ontologies/bibframe/Agent"/>
  </rdf:Description>
  <rdf:Description rdf:nodeID="Nc3008a529f364366b0b4d41a6feadb21">
    <bf:agent rdf:nodeID="Na8d4e2889262436f8674dd1ca36c2872"/>
    <rdf:type rdf:resource="http://id.loc.gov/ontologies/bibframe/Contribution"/>
    <bf:role rdf:resource="http://id.loc.gov/vocabulary/relators/ill"/>
  </rdf:Description>
  <rdf:Description rdf:nodeID="Nea630ffc11ae4601ba8722be2fa76701">
    <rdfs:label xml:lang="eng">Latin</rdfs:label>
    <rdf:type rdf:resource="http://id.loc.gov/ontologies/bibframe/Script"/>
  </rdf:Description>
  <rdf:Description rdf:nodeID="Nc5390653a56549d48c7c816ac03c82d9">
    <rdfs:label xml:lang="eng">Includes bibliographical references (page 261) and index</rdfs:label>
    <rdf:type rdf:resource="http://id.loc.gov/ontologies/bibframe/SupplementaryContent"/>
  </rdf:Description>
</rdf:RDF>
