<?xml version="1.0" encoding="UTF-8"?>
<rdf:RDF
   xmlns:bf="http://id.loc.gov/ontologies/bibframe/"
   xmlns:bflc="http://id.loc.gov/ontologies/bflc/"
   xmlns:owl="http://www.w3.org/2002/07/owl#"
   xmlns:rdf="http://www.w3.org/1999/02/22-rdf-syntax-ns#"
   xmlns:rdfs="http://www.w3.org/2000/01/rdf-schema#"
>
  <rdf:Description rdf:about="https://api.stage.sinopia.io/resource/4244974c-7d7c-4802-9b70-696f3bf1f2cb">
    <bf:identifier rdf:nodeID="Ncd41213351994b57a50814bf85bee098"/>
    <bf:classification rdf:nodeID="Nc082eb1763e24345ab69bb96b3cdbc6d"/>
    <bf:physicalLocation xml:lang="en">Yragui bookshelf</bf:physicalLocation>
    <bf:sublocation rdf:nodeID="Nc3a9d1f52196447889076022a39f1f61"/>
    <bf:heldBy rdf:nodeID="N953b585bb97c4dfeafc9c832020b00ad"/>
    <rdf:type rdf:resource="http://id.loc.gov/ontologies/bibframe/Item"/>
    <bf:adminMetadata rdf:nodeID="N3a2abdf5aad64e6bbd72ec6d9d6eed87"/>
    <bf:immediateAcquisition rdf:nodeID="Ne4fd1a9a61574aee870516890cf83709"/>
    <owl:sameAs rdf:resource="https://api.sinopia.io/resource/b22e4e53-f744-461e-8bef-b9a9a402830d"/>
    <bf:usageAndAccessPolicy rdf:nodeID="N88ebc23a942947b5ba2204c8544e7b94"/>
    <bf:usageAndAccessPolicy rdf:nodeID="Nf1556c307a734e1783c81919c2206c0d"/>
    <bf:itemOf rdf:resource="https://api.sinopia.io/resource/repository/washington/30d6a876-bb4e-44a6-b91c-7c2aa2fb43bc"/>
  </rdf:Description>
  <rdf:Description rdf:nodeID="N88ebc23a942947b5ba2204c8544e7b94">
    <rdf:type rdf:resource="http://id.loc.gov/ontologies/bibframe/AccessPolicy"/>
    <rdfs:label xml:lang="en">Need keys to Yragui house or delivery by Crystal Clements, who is infamously stingy when it comes to loaning out personal copies of her books, especially if she studied them with her favorite late professor, Willis Konick. This is one of those books and you'll probably need to pry it out of her cold, dead fingers. Better to find another copy.</rdfs:label>
  </rdf:Description>
  <rdf:Description rdf:nodeID="N3a2abdf5aad64e6bbd72ec6d9d6eed87">
    <bflc:catalogerID>cec23</bflc:catalogerID>
    <bf:creationDate rdf:datatype="http://www.w3.org/2001/XMLSchema#date">2021-05-04</bf:creationDate>
    <rdf:type rdf:resource="http://id.loc.gov/ontologies/bibframe/AdminMetadata"/>
    <bf:descriptionConventions rdf:resource="https://id.loc.gov/vocabulary/descriptionConventions/rda"/>
    <bf:descriptionLanguage rdf:resource="https://id.loc.gov/vocabulary/languages/eng"/>
    <bf:source rdf:resource="https://id.loc.gov/vocabulary/organizations/wau"/>
    <bflc:encodingLevel rdf:resource="https://id.loc.gov/vocabulary/menclvl/f"/>
    <bf:status rdf:nodeID="N2d5d5f97559e41fc96e6a8464ffb094e"/>
    <bf:generationProcess rdf:nodeID="N7d750c49d7a84cd5b2051ec6bd2dc7e6"/>
  </rdf:Description>
  <rdf:Description rdf:nodeID="Ne4fd1a9a61574aee870516890cf83709">
    <rdf:type rdf:resource="http://id.loc.gov/ontologies/bibframe/ImmediateAcquisition"/>
    <rdfs:label xml:lang="en">Magus Books</rdfs:label>
  </rdf:Description>
  <rdf:Description rdf:nodeID="Ncd41213351994b57a50814bf85bee098">
    <rdf:value xml:lang="en">12345</rdf:value>
    <rdf:type rdf:resource="http://id.loc.gov/ontologies/bibframe/Barcode"/>
  </rdf:Description>
  <rdf:Description rdf:nodeID="N953b585bb97c4dfeafc9c832020b00ad">
    <rdf:type rdf:resource="http://id.loc.gov/ontologies/bibframe/Agent"/>
    <rdfs:label>WAU</rdfs:label>
  </rdf:Description>
  <rdf:Description rdf:nodeID="Nc082eb1763e24345ab69bb96b3cdbc6d">
    <rdf:type rdf:resource="http://id.loc.gov/ontologies/bibframe/ClassificationLcc"/>
    <bf:itemPortion>G6 1955</bf:itemPortion>
    <bf:classificationPortion>PS3511.A86</bf:classificationPortion>
  </rdf:Description>
  <rdf:Description rdf:nodeID="N2d5d5f97559e41fc96e6a8464ffb094e">
    <bf:code>n</bf:code>
    <rdf:type rdf:resource="http://id.loc.gov/ontologies/bibframe/Status"/>
  </rdf:Description>
  <rdf:Description rdf:nodeID="Nc3a9d1f52196447889076022a39f1f61">
    <rdfs:label xml:lang="en">American fiction</rdfs:label>
    <rdf:type rdf:resource="http://id.loc.gov/ontologies/bibframe/Sublocation"/>
  </rdf:Description>
  <rdf:Description rdf:nodeID="N7d750c49d7a84cd5b2051ec6bd2dc7e6">
    <rdfs:label>rml.py SNAPSHOT: 2021-05-04T13:39:17+00:00</rdfs:label>
    <rdf:type rdf:resource="http://id.loc.gov/ontologies/bibframe/GenerationProcess"/>
  </rdf:Description>
  <rdf:Description rdf:nodeID="Nf1556c307a734e1783c81919c2206c0d">
    <rdf:type rdf:resource="http://id.loc.gov/ontologies/bibframe/UsePolicy"/>
    <rdfs:label xml:lang="en">Need permission from Crystal Clements</rdfs:label>
  </rdf:Description>
</rdf:RDF>
