[
  {
    "@id": "https://api.sinopia.io/resource/20d58559-42c0-4022-81dc-8071e1a9b523",
    "@type": [
      "http://id.loc.gov/ontologies/bibframe/Title"
    ],
    "http://id.loc.gov/ontologies/bibframe/mainTitle": [
      {
        "@language": "rus",
        "@value": "Нашимъ дѣтям"
      }
    ],
    "http://id.loc.gov/ontologies/bibframe/subtitle": [
      {
        "@language": "rus",
        "@value": "хрестоматія на русскомъ языкѣ для еврейскихъ дѣтей въ школѣ и семьѣ"
      }
    ]
  }
]