[
  {
    "@id": "https://api.sinopia.io/resource/92716925-79c4-4959-860f-221aff7adf91",
    "@type": [
      "http://id.loc.gov/ontologies/bibframe/Instance"
    ],
    "http://id.loc.gov/ontologies/bibframe/adminMetadata": [
      {
        "@id": "https://api.sinopia.io/resource/4b513f97-5948-4db0-9aaf-adb947eea194"
      }
    ],
    "http://id.loc.gov/ontologies/bibframe/appliedMaterial": [
      {
        "@id": "http://rdaregistry.info/termList/RDAMaterial/1017"
      }
    ],
    "http://id.loc.gov/ontologies/bibframe/baseMaterial": [
      {
        "@id": "http://rdaregistry.info/termList/RDAMaterial/1025"
      }
    ],
    "http://id.loc.gov/ontologies/bibframe/carrier": [
      {
        "@id": "http://www.rdaregistry.info/termList/RDACarrierType/1049"
      }
    ],
    "http://id.loc.gov/ontologies/bibframe/copyrightDate": [
      {
        "@type": "http://www.w3.org/2001/XMLSchema#gYear",
        "@value": "©1980"
      }
    ],
    "http://id.loc.gov/ontologies/bibframe/dimensions": [
      {
        "@language": "eng",
        "@value": "23 cm"
      }
    ],
    "http://id.loc.gov/ontologies/bibframe/extent": [
      {
        "@id": "https://api.sinopia.io/resource/06b42b0f-43b3-4d9f-ad54-241e6ca83ad6"
      }
    ],
    "http://id.loc.gov/ontologies/bibframe/instanceOf": [
      {
        "@id": "https://api.sinopia.io/resource/ae7793a0-35f6-4f82-bf0e-d3c29a4cb7f6"
      }
    ],
    "http://id.loc.gov/ontologies/bibframe/issuance": [
      {
        "@id": "http://rdaregistry.info/termList/ModeIssue/1001"
      }
    ],
    "http://id.loc.gov/ontologies/bibframe/media": [
      {
        "@id": "http://rdaregistry.info/termList/RDAMediaType/1007"
      }
    ],
    "http://id.loc.gov/ontologies/bibframe/provisionActivity": [
      {
        "@id": "https://api.sinopia.io/resource/60bd64ca-016a-4d7a-9add-363540a6d056"
      }
    ],
    "http://id.loc.gov/ontologies/bibframe/provisionActivityStatement": [
      {
        "@language": "eng",
        "@value": "Seattle ; London : University of Washington Press, [1980]"
      }
    ],
    "http://id.loc.gov/ontologies/bibframe/responsibilityStatement": [
      {
        "@language": "eng",
        "@value": "Sally B. Woodbridge and Roger Montgomery ; essay on landscape design by David S. Streatfield."
      }
    ],
    "http://id.loc.gov/ontologies/bibframe/title": [
      {
        "@id": "https://api.sinopia.io/resource/c20cebd1-df79-4edb-b1b4-741b3a6429fb"
      }
    ]
  }
]