<?xml version="1.0" encoding="UTF-8"?>
<rdf:RDF
   xmlns:bf="http://id.loc.gov/ontologies/bibframe/"
   xmlns:bflc="http://id.loc.gov/ontologies/bflc/"
   xmlns:owl="http://www.w3.org/2002/07/owl#"
   xmlns:rdf="http://www.w3.org/1999/02/22-rdf-syntax-ns#"
   xmlns:rdfs="http://www.w3.org/2000/01/rdf-schema#"
>
  <rdf:Description rdf:nodeID="N04f58e5980d64b5d930bfa4f06385e95">
    <bf:date rdf:datatype="http://www.w3.org/2001/XMLSchema#gYear">1986-01-01</bf:date>
    <bf:place rdf:nodeID="N969344ef4c3f45b495591871b92ac4ff"/>
    <bf:agent rdf:nodeID="N73a8f768252d4e7bb29598828c674d77"/>
    <rdf:type rdf:resource="http://id.loc.gov/ontologies/bibframe/Publication"/>
  </rdf:Description>
  <rdf:Description rdf:nodeID="Nf4f46b4611124a099a0831ce7a5d3d93">
    <bf:code>n</bf:code>
    <rdf:type rdf:resource="http://id.loc.gov/ontologies/bibframe/Status"/>
  </rdf:Description>
  <rdf:Description rdf:nodeID="Ncaff12badadc43589920934260452eba">
    <bf:descriptionLanguage rdf:resource="https://id.loc.gov/vocabulary/languages/eng"/>
    <rdf:type rdf:resource="http://id.loc.gov/ontologies/bibframe/AdminMetadata"/>
    <bf:source rdf:resource="https://id.loc.gov/vocabulary/organizations/wau"/>
    <bf:status rdf:nodeID="Nf4f46b4611124a099a0831ce7a5d3d93"/>
    <bflc:catalogerID xml:lang="eng">dbrookin</bflc:catalogerID>
    <bf:descriptionConventions rdf:resource="https://id.loc.gov/vocabulary/descriptionConventions/rda"/>
    <bflc:encodingLevel rdf:resource="https://id.loc.gov/vocabulary/menclvl/f"/>
    <bf:generationProcess rdf:nodeID="N90031079ee2243c0ab5d876a2347173a"/>
    <bf:creationDate rdf:datatype="http://www.w3.org/2001/XMLSchema#date">2020-02-18</bf:creationDate>
  </rdf:Description>
  <rdf:Description rdf:about="https://api.sinopia.io/resource/fe6bd5d5-1471-40c5-8aeb-7aab75bf7bb6">
    <bf:carrier rdf:resource="http://www.rdaregistry.info/termList/RDACarrierType/1008"/>
    <bf:instanceOf rdf:resource="https://api.sinopia.io/resource/75019fc8-4236-4a6e-aeb8-4f3191eb35f8"/>
    <bf:provisionActivity rdf:nodeID="N04f58e5980d64b5d930bfa4f06385e95"/>
    <bf:adminMetadata rdf:nodeID="Ncaff12badadc43589920934260452eba"/>
    <bf:responsibilityStatement xml:lang="rus">фотографии автора</bf:responsibilityStatement>
    <rdf:type rdf:resource="http://id.loc.gov/ontologies/bibframe/Instance"/>
    <bf:responsibilityStatement xml:lang="rus">Александр Миловский</bf:responsibilityStatement>
    <bf:title rdf:nodeID="N169503630dc34ad9bf07d8357ef6ee0d"/>
    <bf:appliedMaterial rdf:resource="http://rdaregistry.info/termList/RDAMaterial/1017"/>
    <bf:media rdf:resource="http://rdaregistry.info/termList/RDAMediaType/1007"/>
    <bf:title rdf:nodeID="Nd14b628f31cc45cdab22212b508155a5"/>
    <bf:baseMaterial rdf:resource="http://rdaregistry.info/termList/RDAMaterial/1025"/>
    <bf:issuance rdf:resource="http://rdaregistry.info/termList/ModeIssue/1001"/>
    <bf:extent rdf:nodeID="Nd962f4689f274deab4623de1557a4a8c"/>
    <owl:sameAs rdf:resource="https://api.sinopia.io/resource/fe6bd5d5-1471-40c5-8aeb-7aab75bf7bb6"/>
  </rdf:Description>
  <rdf:Description rdf:nodeID="N90031079ee2243c0ab5d876a2347173a">
    <rdfs:label rdf:datatype="http://www.w3.org/2001/XMLSchema#dateTime">rml.py SNAPSHOT: 2021-03-18T15:41:14+00:00</rdfs:label>
    <rdf:type rdf:resource="http://id.loc.gov/ontologies/bibframe/GenerationProcess"/>
  </rdf:Description>
  <rdf:Description rdf:nodeID="N169503630dc34ad9bf07d8357ef6ee0d">
    <rdf:type rdf:resource="http://id.loc.gov/ontologies/bibframe/VariantTitle"/>
    <bf:mainTitle xml:lang="rus">Skachi, dobryĭ edinorog : ocherki</bf:mainTitle>
    <rdfs:label xml:lang="rus">Skachi, dobryĭ edinorog : ocherki</rdfs:label>
  </rdf:Description>
  <rdf:Description rdf:nodeID="N969344ef4c3f45b495591871b92ac4ff">
    <rdfs:label xml:lang="rus">Москва</rdfs:label>
    <rdf:type rdf:resource="http://id.loc.gov/ontologies/bibframe/Place"/>
  </rdf:Description>
  <rdf:Description rdf:nodeID="Nd962f4689f274deab4623de1557a4a8c">
    <rdfs:label xml:lang="eng">189 pages</rdfs:label>
    <rdf:type rdf:resource="http://id.loc.gov/ontologies/bibframe/Extent"/>
  </rdf:Description>
  <rdf:Description rdf:nodeID="Nd14b628f31cc45cdab22212b508155a5">
    <rdf:type rdf:resource="http://id.loc.gov/ontologies/bibframe/Title"/>
    <bf:mainTitle xml:lang="rus">Скачи, добрый единорог</bf:mainTitle>
    <bf:subtitle xml:lang="rus">очерки</bf:subtitle>
  </rdf:Description>
  <rdf:Description rdf:nodeID="N73a8f768252d4e7bb29598828c674d77">
    <rdf:type rdf:resource="http://id.loc.gov/ontologies/bibframe/Agent"/>
    <rdfs:label xml:lang="rus">Детская литература</rdfs:label>
  </rdf:Description>
</rdf:RDF>
