<rdf:RDF xmlns:ns1="http://id.loc.gov/ontologies/bibframe/" xmlns:rdf="http://www.w3.org/1999/02/22-rdf-syntax-ns#">
  <rdf:Description rdf:about="https://api.sinopia.io/resource/2c164c23-bf29-4c1f-8f0b-d6a3a55f0a51">
    <ns1:carrier rdf:resource="http://rdaregistry.info/termList/RDACarrierType/1018" />
    <ns1:title rdf:resource="https://api.sinopia.io/resource/a7cfac58-9a16-47d7-8cc6-1eaf8e5379c1" /><rdf:type rdf:resource="http://id.loc.gov/ontologies/bibframe/Instance" />
    <ns1:digitalCharacteristic rdf:resource="http://rdaregistry.info/termList/fileType/1002" />
    <ns1:provisionActivityStatement xml:lang="eng">[Seattle, Washington] : [University of Washington Libraries], [2019]</ns1:provisionActivityStatement>
    <ns1:digitalCharacteristic rdf:resource="https://api.sinopia.io/resource/00d74cdc-5d7a-4478-afd0-a6f508374532" /><ns1:adminMetadata rdf:resource="https://api.sinopia.io/resource/a79d2f0b-8e12-435f-af96-36a4820fe18d" /><ns1:copyrightDate rdf:datatype="http://www.w3.org/2001/XMLSchema#gYear">&#169;2019</ns1:copyrightDate>
    <ns1:responsibilityStatement xml:lang="eng">Ashley Bagley</ns1:responsibilityStatement>
    <ns1:hasItem rdf:resource="https://api.sinopia.io/resource/2881ed78-4370-4bef-b9ba-a71e65fdae51" /><ns1:issuance rdf:resource="http://rdaregistry.info/termList/ModeIssue/1001" />
    <ns1:instanceOf rdf:resource="https://api.sinopia.io/resource/87d03a18-cdd8-4ae3-aff5-b7a6e99d5085" />
    <ns1:media rdf:resource="http://rdaregistry.info/termList/RDAMediaType/1003" />
    <ns1:provisionActivity rdf:resource="https://api.sinopia.io/resource/2254415d-ffe7-460c-a279-65be4adf291e" /></rdf:Description>
  </rdf:RDF>