[
  {
    "@id": "https://api.sinopia.io/resource/4d35000b-7b99-43de-8c87-fbe8bb574e82",
    "@type": [
      "http://id.loc.gov/ontologies/bibframe/Identifier"
    ],
    "http://id.loc.gov/ontologies/bibframe/note": [
      {
        "@id": "_:Nad217e3b881d43e19f6d697e2d5e3b21"
      }
    ],
    "http://id.loc.gov/ontologies/bibframe/source": [
      {
        "@id": "https://api.sinopia.io/resource/a9e32bfc-517c-4012-9e90-d2e1a7035e2f"
      }
    ],
    "http://www.w3.org/1999/02/22-rdf-syntax-ns#value": [
      {
        "@language": "chi",
        "@value": "Yin, Tiechao, 1958- Chaoxian yu yu Tonggusi yu guan xi yan jiu"
      }
    ]
  },
  {
    "@id": "_:Nad217e3b881d43e19f6d697e2d5e3b21"
  }
]