<?xml version="1.0" encoding="UTF-8"?>
<rdf:RDF
   xmlns:bf="http://id.loc.gov/ontologies/bibframe/"
   xmlns:bflc="http://id.loc.gov/ontologies/bflc/"
   xmlns:madsrdf="http://www.loc.gov/mads/rdf/v1#"
   xmlns:owl="http://www.w3.org/2002/07/owl#"
   xmlns:rdae="http://rdaregistry.info/Elements/e/"
   xmlns:rdf="http://www.w3.org/1999/02/22-rdf-syntax-ns#"
   xmlns:sin="http://sinopia.io/vocabulary/"
>
  <rdf:Description rdf:about="https://api.sinopia.io/resource/4820e1d1-353f-4baa-a1b6-980eaae469e1">
    <owl:sameAs rdf:resource="https://api.sinopia.io/resource/ff6de7bc-3594-4dc4-8110-d70275c9685a"/>
    <rdae:P20206 xml:lang="eng">Includes bibliographical references (pages 266-270) and index.</rdae:P20206>
    <madsrdf:isIdentifiedByAuthority>n  81138329</madsrdf:isIdentifiedByAuthority>
    <rdae:P20231 rdf:resource="https://api.sinopia.io/resource/251393a8-33fb-44fd-827e-a75328c3fbaa"/>
    <rdae:P20207 rdf:resource="http://id.loc.gov/vocabulary/millus/ill"/>
    <bf:adminMetadata rdf:nodeID="Ncfa0b1248a3c42fa9974add3ba7e279a"/>
    <rdae:P20006 rdf:resource="http://id.loc.gov/vocabulary/languages/eng"/>
    <rdae:P20214 xml:lang="eng">1978</rdae:P20214>
    <sin:hasResourceTemplate>WAU:RT:RDA:Expression:monograph</sin:hasResourceTemplate>
    <rdae:P20065 xml:lang="eng">Latin</rdae:P20065>
    <rdae:P20001 rdf:resource="http://rdaregistry.info/termList/RDAContentType/1020"/>
    <rdae:P20224 rdf:resource="http://rdaregistry.info/termList/RDAColourContent/1002"/>
    <rdf:type rdf:resource="http://rdaregistry.info/Elements/c/C10006"/>
  </rdf:Description>
  <rdf:Description rdf:nodeID="Ndf327f97157c4b32becb4c957b64557a">
    <bf:code xml:lang="eng">n</bf:code>
    <rdf:type rdf:resource="http://id.loc.gov/ontologies/bibframe/Status"/>
  </rdf:Description>
  <rdf:Description rdf:nodeID="Ncfa0b1248a3c42fa9974add3ba7e279a">
    <bf:descriptionConventions rdf:resource="https://id.loc.gov/vocabulary/descriptionConventions/rda"/>
    <bf:creationDate xml:lang="eng">2020-05-06</bf:creationDate>
    <bf:source rdf:resource="https://id.loc.gov/vocabulary/organizations/wau"/>
    <bf:descriptionAuthentication rdf:resource="http://id.loc.gov/vocabulary/marcauthen/pcc"/>
    <bf:status rdf:nodeID="Ndf327f97157c4b32becb4c957b64557a"/>
    <bf:descriptionLanguage rdf:resource="https://id.loc.gov/vocabulary/languages/eng"/>
    <rdf:type rdf:resource="http://id.loc.gov/ontologies/bibframe/AdminMetadata"/>
    <bflc:catalogerID xml:lang="eng">pfreeman</bflc:catalogerID>
    <bflc:encodingLevel rdf:resource="https://id.loc.gov/vocabulary/menclvl/f"/>
  </rdf:Description>
</rdf:RDF>
