<?xml version="1.0" encoding="UTF-8"?>
<rdf:RDF
   xmlns:bf="http://id.loc.gov/ontologies/bibframe/"
   xmlns:bflc="http://id.loc.gov/ontologies/bflc/"
   xmlns:owl="http://www.w3.org/2002/07/owl#"
   xmlns:rdf="http://www.w3.org/1999/02/22-rdf-syntax-ns#"
   xmlns:rdfs="http://www.w3.org/2000/01/rdf-schema#"
>
  <rdf:Description rdf:nodeID="Nfdb5611f182c4ac395fa4d3fd4c327b8">
    <rdf:type rdf:resource="http://id.loc.gov/ontologies/bibframe/Status"/>
    <bf:code>n</bf:code>
  </rdf:Description>
  <rdf:Description rdf:nodeID="N697c20e8b073404f8a1f0f1a8f73e96c">
    <rdf:type rdf:resource="http://id.loc.gov/ontologies/bibframe/GenerationProcess"/>
    <rdfs:label rdf:datatype="http://www.w3.org/2001/XMLSchema#dateTime">rml.py SNAPSHOT: 2021-04-14T14:01:07+00:00</rdfs:label>
  </rdf:Description>
  <rdf:Description rdf:about="https://api.stage.sinopia.io/resource/09f1c894-d05d-461a-8ca8-bf3f4315b6cb">
    <rdf:type rdf:resource="http://id.loc.gov/ontologies/bibframe/Work"/>
    <bf:illustrativeContent rdf:resource="http://id.loc.gov/vocabulary/millus/ill"/>
    <bf:colorContent rdf:nodeID="Ne9ba8043db4f417582ab91e88be7935d"/>
    <bf:notation rdf:nodeID="N8797521df96c4202881886ea9f5c3ff6"/>
    <owl:sameAs rdf:resource="https://api.sinopia.io/resource/700dcd07-2ba5-4360-80a0-75339178addf"/>
    <bf:adminMetadata rdf:nodeID="N24d0f0bc12964ac29431536ee775375e"/>
    <bf:expressionOf rdf:resource="https://api.sinopia.io/resource/869202f2-b1de-4bce-9737-8e50e73ffcf1"/>
    <bf:content rdf:resource="http://rdaregistry.info/termList/RDAContentType/1020"/>
  </rdf:Description>
  <rdf:Description rdf:nodeID="N24d0f0bc12964ac29431536ee775375e">
    <bf:status rdf:nodeID="Nfdb5611f182c4ac395fa4d3fd4c327b8"/>
    <bf:source rdf:resource="https://id.loc.gov/vocabulary/organizations/wau"/>
    <bflc:catalogerID xml:lang="eng">dbrookin</bflc:catalogerID>
    <bf:generationProcess rdf:nodeID="N697c20e8b073404f8a1f0f1a8f73e96c"/>
    <bf:descriptionConventions rdf:resource="https://id.loc.gov/vocabulary/descriptionConventions/rda"/>
    <rdf:type rdf:resource="http://id.loc.gov/ontologies/bibframe/AdminMetadata"/>
    <bf:creationDate rdf:datatype="http://www.w3.org/2001/XMLSchema#date">2020-02-18</bf:creationDate>
    <bf:descriptionLanguage rdf:resource="https://id.loc.gov/vocabulary/languages/eng"/>
    <bflc:encodingLevel rdf:resource="https://id.loc.gov/vocabulary/menclvl/f"/>
  </rdf:Description>
  <rdf:Description rdf:nodeID="N8797521df96c4202881886ea9f5c3ff6">
    <rdf:type rdf:resource="http://id.loc.gov/ontologies/bibframe/Script"/>
    <rdfs:label xml:lang="eng">Cyrillic</rdfs:label>
  </rdf:Description>
  <rdf:Description rdf:nodeID="Ne9ba8043db4f417582ab91e88be7935d">
    <rdfs:label>color</rdfs:label>
    <rdf:type rdf:resource="http://id.loc.gov/ontologies/bibframe/ColorContent"/>
  </rdf:Description>
</rdf:RDF>
