<?xml version="1.0" encoding="UTF-8"?>
<rdf:RDF
   xmlns:bf="http://id.loc.gov/ontologies/bibframe/"
   xmlns:bflc="http://id.loc.gov/ontologies/bflc/"
   xmlns:rdam="http://rdaregistry.info/Elements/m/"
   xmlns:rdamdt="http://rdaregistry.info/Elements/m/datatype/"
   xmlns:rdax="https://doi.org/10.6069/uwlib.55.d.4#"
   xmlns:rdf="http://www.w3.org/1999/02/22-rdf-syntax-ns#"
   xmlns:sin="http://sinopia.io/vocabulary/"
>
  <rdf:Description rdf:about="https://api.sinopia.io/resource/c85b46a5-8af1-420b-a393-99ebb60f3d72">
    <bf:adminMetadata rdf:nodeID="N1ad3b5400e2e4eaca43058b2209ff644"/>
    <rdax:heldBy rdf:resource="https://id.loc.gov/vocabulary/organizations/wau"/>
    <rdf:type rdf:resource="http://rdaregistry.info/Elements/c/C10007"/>
    <rdam:P30139 rdf:resource="https://api.sinopia.io/resource/46ee55f3-68fa-4a86-a614-a8a0f850c27e"/>
    <rdam:P30176 xml:lang="en">Birkhaüser</rdam:P30176>
    <rdam:P30084 rdf:resource="http://rdaregistry.info/termList/RDAMaterial/1017"/>
    <rdam:P30011 xml:lang="en">[2018]</rdam:P30011>
    <rdam:P30007 xml:lang="en">©2018</rdam:P30007>
    <rdamdt:P30004 xml:lang="en">9781493977062</rdamdt:P30004>
    <rdax:hasLcClassificationPartB xml:lang="en">.B49 2018</rdax:hasLcClassificationPartB>
    <rdam:P30169 xml:lang="en">25 cm</rdam:P30169>
    <rdam:P30014 xml:lang="en">volume 14</rdam:P30014>
    <rdam:P30088 xml:lang="en">New York, NY</rdam:P30088>
    <rdam:P30157 xml:lang="en">Einstein studies</rdam:P30157>
    <rdam:P30156 xml:lang="en">Beyond Einstein</rdam:P30156>
    <rdam:P30002 rdf:resource="http://rdaregistry.info/termList/RDAMediaType/1007"/>
    <rdam:P30182 xml:lang="en">xxiii, 492 pages</rdam:P30182>
    <rdax:hasLcClassificationPartA xml:lang="en">QC173.52</rdax:hasLcClassificationPartA>
    <rdam:P30003 rdf:resource="http://rdaregistry.info/termList/ModeIssue/1001"/>
    <rdam:P30208 rdf:resource="http://rdaregistry.info/termList/RDAMaterial/1025"/>
    <sin:hasResourceTemplate>WAU:RT:RDA:Manifestation:monograph</sin:hasResourceTemplate>
    <rdamdt:P30004 xml:lang="en">1493977067</rdamdt:P30004>
    <rdam:P30105 xml:lang="en">David E. Rowe, Tilman Sauer, Scott A. Walter, editors</rdam:P30105>
    <rdam:P30001 rdf:resource="http://www.rdaregistry.info/termList/RDACarrierType/1008"/>
    <rdam:P30142 xml:lang="en">perspectives on geometry, gravitation, and cosmology in the twentieth century</rdam:P30142>
  </rdf:Description>
  <rdf:Description rdf:nodeID="N1ad3b5400e2e4eaca43058b2209ff644">
    <bflc:encodingLevel rdf:resource="https://id.loc.gov/vocabulary/menclvl/f"/>
    <rdf:type rdf:resource="http://id.loc.gov/ontologies/bibframe/AdminMetadata"/>
    <bf:descriptionLanguage rdf:resource="https://id.loc.gov/vocabulary/languages/eng"/>
    <bf:status rdf:nodeID="N0ecb85e1e84c4b5ea8e5b16048f4a657"/>
    <bflc:catalogerID xml:lang="en">cec23</bflc:catalogerID>
    <bf:descriptionConventions rdf:resource="https://id.loc.gov/vocabulary/descriptionConventions/rda"/>
    <bf:source rdf:resource="https://id.loc.gov/vocabulary/organizations/wau"/>
    <bf:creationDate xml:lang="en">2019-11-20</bf:creationDate>
  </rdf:Description>
  <rdf:Description rdf:nodeID="N0ecb85e1e84c4b5ea8e5b16048f4a657">
    <bf:code xml:lang="en">n</bf:code>
    <rdf:type rdf:resource="http://id.loc.gov/ontologies/bibframe/Status"/>
  </rdf:Description>
</rdf:RDF>
